Metadata-Version: 2.1
Name: rjob
Version: 1.2
Summary: Dummy simple remote task executor
Home-page: https://github.com/reddec/rjob
Author: Baryshnikov Aleksandr (reddec)
Author-email: owner@reddec.net
License: UNKNOWN
Platform: UNKNOWN
Classifier: Programming Language :: Python :: 3.5
Classifier: Operating System :: POSIX
Classifier: License :: OSI Approved :: Apache Software License
Classifier: Topic :: System :: Distributed Computing
